caravagene/__init__.py
caravagene/caravagene.py
caravagene/cli.py
caravagene/template.html
caravagene/version.py
caravagene/symbols/ATG.svg
caravagene/symbols/CDS.svg
caravagene/symbols/DNA-binding-element.svg
caravagene/symbols/IRES.svg
caravagene/symbols/ITR.svg
caravagene/symbols/LTR.svg
caravagene/symbols/RBS.svg
caravagene/symbols/RNA-stability-sequence.svg
caravagene/symbols/UTR.svg
caravagene/symbols/backbone.svg
caravagene/symbols/blank.svg
caravagene/symbols/etc.svg
caravagene/symbols/expression-cassette.svg
caravagene/symbols/five-prime-overhang.svg
caravagene/symbols/homology-arm.svg
caravagene/symbols/insulator.svg
caravagene/symbols/none.svg
caravagene/symbols/origin-of-replication.svg
caravagene/symbols/p2A.svg
caravagene/symbols/part-linker.svg
caravagene/symbols/peptide-linker.svg
caravagene/symbols/promoter.svg
caravagene/symbols/protein-tag.svg
caravagene/symbols/recombinase-recognition-sequence-directed.svg
caravagene/symbols/recombinase-recognition-sequence.svg
caravagene/symbols/restriction-enzyme-recognition-site.svg
caravagene/symbols/signal-peptide.svg
caravagene/symbols/terminator.svg
caravagene/symbols/three-prime-overhang.svg
caravagene/symbols/user-defined.svg
caravagene-0.1.9.dist-info/licenses/LICENCE.txt
examples/construct_jpeg.py
examples/from_json.py
examples/from_spreadsheet.py
examples/multiconstruct_pdf.py
tests/test_caravagene.py
caravagene-0.1.9.dist-info/METADATA
caravagene-0.1.9.dist-info/WHEEL
caravagene-0.1.9.dist-info/entry_points.txt
caravagene-0.1.9.dist-info/top_level.txt
caravagene-0.1.9.dist-info/RECORD
