Metadata-Version: 2.4
Name: caravagene
Version: 0.1.9
Summary: Plot multi-part genetic constructs.
Author: Zulko
License-Expression: MIT
Project-URL: Homepage, https://github.com/Edinburgh-Genome-Foundry/Caravagene
Keywords: SBOL,DNA,assembly,plot
License-File: LICENCE.txt
Requires-Dist: docopt
Requires-Dist: openpyxl
Requires-Dist: jinja2
Requires-Dist: pandas
Provides-Extra: cli
Requires-Dist: watchdog; extra == "cli"
Dynamic: license-file
